{
    "m_Version": 4,
    "DisplayName": "#STR_EXPANSION_MARKET_CATEGORY_HOLSTERS",
    "Items": [
        {
            "ClassName": "chestholster",
            "MaxPriceThreshold": 120,
            "MinPriceThreshold": 60,
            "MaxStockThreshold": 100,
            "MinStockThreshold": 1,
            "PurchaseType": 0,
            "SpawnAttachments": [],
            "Variants": []
        },
        {
            "ClassName": "platecarrierholster",
            "MaxPriceThreshold": 120,
            "MinPriceThreshold": 60,
            "MaxStockThreshold": 100,
            "MinStockThreshold": 1,
            "PurchaseType": 0,
            "SpawnAttachments": [],
            "Variants": []
        },
        {
            "ClassName": "platecarrierpouches",
            "MaxPriceThreshold": 200,
            "MinPriceThreshold": 100,
            "MaxStockThreshold": 100,
            "MinStockThreshold": 1,
            "PurchaseType": 0,
            "SpawnAttachments": [],
            "Variants": []
        },
        {
            "ClassName": "nylonknifesheath",
            "MaxPriceThreshold": 60,
            "MinPriceThreshold": 30,
            "MaxStockThreshold": 100,
            "MinStockThreshold": 1,
            "PurchaseType": 0,
            "SpawnAttachments": [],
            "Variants": []
        }
    ]
}