{
    "m_Version": 6,
    "TraderName": "AlakitWeapons",
    "DisplayName": "#STR_EXPANSION_MARKET_TRADER_WEAPONS",
    "TraderIcon": "Shotgun",
    "Currencies": [
        "expansiongoldbar",
        "expansiongoldnugget",
        "expansionsilverbar",
        "expansionsilvernugget"
    ],
    "Items": {
        "izh43shotgun": 1,
        "expansion_dt11": 1,

        "ammo_12gaslug": 1,
        "ammobox_12gaslug_10rnd": 1,
        "ammo_12gapellets": 1,
        "ammobox_00buck_10rnd": 1,		
        "ammo_12garubberslug": 1,
        "ammobox_12garubberslug_10rnd": 1,

		
        "winchester70": 1,
        "cz527": 1,
        "mosin9130": 1,
        "repeater": 1,
        "b95": 1,
        "izh18": 1,
        "ruger1022": 1,		
        "expansion_crossbow": 1,		
        "expansion_ammo_arrowbolt": 1,
        "ammo_308wintracer": 1,		
        "ammobox_308wintracer_20rnd": 1,
        "ammobox_308win_20rnd": 1,
        "ammo_308win": 1,
        "ammo_762x39": 1,
        "ammobox_762x39tracer_20rnd": 1,
        "ammobox_762x39_20rnd": 1,
        "ammo_762x39tracer": 1,
        "ammo_762x54": 1,		
        "ammo_762x54tracer": 1,
        "ammobox_762x54_20rnd": 1,
        "ammobox_762x54tracer_20rnd": 1,
        "ammo_357": 1,
        "ammobox_357_20rnd": 1,
        "mag_ruger1022_30rnd": 1,
        "mag_ruger1022_15rnd": 1,
        "mag_cz527_5rnd": 1,
        "mosin_compensator": 1,
		
        "makarovij70": 1,		
        "colt1911": 1,
        "expansion_longhorn": 1,		
        "ammo_380": 1,
        "ammobox_380_35rnd": 1,
        "ammo_45acp": 1,
        "ammobox_45acp_25rnd": 1,
        "mag_1911_7rnd": 1,
        "mag_ij70_8rnd": 1,		
		
        "kitchenknife": 1,
        "stunbaton": 1,
        "steakknife": 1,
        "cattleprod": 1,
        "broom_birch": 1,
        "baseballbat": 1,
        "huntingknife": 1,
        "broom": 1,
		
        "flaregun": 1,
        "ammo_flare": 1,
        "ammo_flaregreen": 1,
        "ammo_flarered": 1,
        "ammo_flareblue": 1,

        "puscopeoptic": 1,
        "huntingoptic": 1,
        "pistoloptic": 1,
		
		"bonehook": 1,
        "mackerel": 1,
        "hook": 1,
        "sardines": 1,
        "worm": 1,
        "carp": 1,
        "fishingrod": 1,
		
		        "sodacan_cola": 1,
        "expansionbread1": 1,
        "vodka": 1,
        "expansionbread3": 1,
        "wolfsteakmeat": 1,
        "tomato": 1,
        "honey": 1,
        "marmalade": 1,
        "greenbellpepper": 1,
        "caninaberry": 1,
        "powderedmilk": 1,
        "expansionbread2": 1,
        "pate": 1,
        "spaghettican": 1,
        "tunacan": 1,
        "amanitamushroom": 1,
        "brisketspread": 1,
        "sambucusberry": 1,
        "sodacan_fronta": 1,
        "rice": 1,
        "psilocybemushroom": 1,
        "lactariusmushroom": 1,
        "cowsteakmeat": 1,
        "boarsteakmeat": 1,
        "slicedpumpkin": 1,
        "saltysticks": 1,
        "potatoseed": 1,
        "lunchmeat": 1,
        "zagorkychocolate": 1,
        "catfoodcan": 1,
        "plum": 1,
        "zucchini": 1,
        "rabbitlegmeat": 1,
        "sodacan_kvass": 1,
        "potato": 1,
        "zagorkypeanuts": 1,
        "crackers": 1,
        "carpfilletmeat": 1,
        "canteen": 1,
        "bearsteakmeat": 1,
        "goatsteakmeat": 1,
        "auriculariamushroom": 1,
        "pear": 1,
        "chickenbreastmeat": 1,
        "deersteakmeat": 1,
        "boletusmushroom": 1,
        "agaricusmushroom": 1,
        "tacticalbaconcan": 1,
        "macrolepiotamushroom": 1,
        "sheepsteakmeat": 1,
        "porkcan": 1,
        "zagorky": 1,
        "pajka": 1,
        "chips": 1,
        "peachescan": 1,
        "dogfoodcan": 1,
        "pumpkin": 1,
        "sodacan_pipsi": 1,
        "pigsteakmeat": 1,
        "expansioncheese1": 1,
        "expansioncheese2": 1,
        "expansioncheese3": 1,
        "expansioncheese4": 1,
        "apple": 1,
        "boxcerealcrunchin": 1,
        "expansionmilkbottle": 1,
        "sodacan_spite": 1,
        "sardinescan": 1,
        "pleurotusmushroom": 1,
        "unknownfoodcan": 1,
        "waterbottle": 1,
        "bakedbeanscan": 1,
        "mackerelfilletmeat": 1
		
		"bandagedressing": 1,
        "disinfectantalcohol": 1,
        "purificationtablets": 1,
        "charcoaltablets": 1,
        "painkillertablets": 1,
        "heatpack": 1,
        "thermometer": 1,
        "vitaminbottle": 1,
        "disinfectantspray": 1
    }
}